setup.py
gremlinpy/__init__.py
gremlinpy/config.py
gremlinpy/exception.py
gremlinpy/gremlin.py
gremlinpy/statement.py
gremlinpy/version.py
gremlinpy.egg-info/PKG-INFO
gremlinpy.egg-info/SOURCES.txt
gremlinpy.egg-info/dependency_links.txt
gremlinpy.egg-info/requires.txt
gremlinpy.egg-info/top_level.txt
gremlinpy/tests/__init__.py
gremlinpy/tests/gremlin.py
gremlinpy/tests/statement.py